firebase_encrypt/__init__.py
firebase_encrypt/__main__.py
firebase_encrypt/create.py
firebase_encrypt/decrypt.py
firebase_encrypt/encrypt.py
firebase_encrypt/sync.py
cryptobase-0.0.1.dist-info/METADATA
cryptobase-0.0.1.dist-info/WHEEL
cryptobase-0.0.1.dist-info/entry_points.txt
cryptobase-0.0.1.dist-info/top_level.txt
cryptobase-0.0.1.dist-info/RECORD
